headsup.py
setup.py
headsup.egg-info/PKG-INFO
headsup.egg-info/SOURCES.txt
headsup.egg-info/dependency_links.txt
headsup.egg-info/entry_points.txt
headsup.egg-info/not-zip-safe
headsup.egg-info/top_level.txt